odoo8_addon_stock_analysis_forecast-8.0.1.0.0.99.dev12-py2.7-nspkg.pth
odoo8_addon_stock_analysis_forecast-8.0.1.0.0.99.dev12.dist-info/DESCRIPTION.rst
odoo8_addon_stock_analysis_forecast-8.0.1.0.0.99.dev12.dist-info/METADATA
odoo8_addon_stock_analysis_forecast-8.0.1.0.0.99.dev12.dist-info/RECORD
odoo8_addon_stock_analysis_forecast-8.0.1.0.0.99.dev12.dist-info/WHEEL
odoo8_addon_stock_analysis_forecast-8.0.1.0.0.99.dev12.dist-info/metadata.json
odoo8_addon_stock_analysis_forecast-8.0.1.0.0.99.dev12.dist-info/namespace_packages.txt
odoo8_addon_stock_analysis_forecast-8.0.1.0.0.99.dev12.dist-info/top_level.txt
odoo_addons/stock_analysis_forecast/README.rst
odoo_addons/stock_analysis_forecast/__init__.py
odoo_addons/stock_analysis_forecast/__openerp__.py
odoo_addons/stock_analysis_forecast/models/__init__.py
odoo_addons/stock_analysis_forecast/models/report_stock_forecast.py
odoo_addons/stock_analysis_forecast/security/ir.model.access.csv
odoo_addons/stock_analysis_forecast/static/description/forecast.png
odoo_addons/stock_analysis_forecast/static/description/icon.png
odoo_addons/stock_analysis_forecast/views/report_stock_forecast.xml
