Metadata-Version: 2.0
Name: odoo8-addon-stock-analysis-forecast
Version: 8.0.1.0.0.99.dev12
Summary: Analysis wiew for stock forecast
Home-page: https://www.agilebg.com
Author: Odoo S.A,Agile Business Group,Odoo Community Association (OCA)
Author-email: support@odoo-community.org
License: LGPL-3
Platform: UNKNOWN
Classifier: Programming Language :: Python :: 2.7
Classifier: Framework :: Odoo
Classifier: License :: OSI Approved :: GNU Lesser General Public License v3 (LGPLv3)
Requires-Dist: odoo (<9.0a,>=8.0a)
